README
README.txt
setup.py
yaco/__init__.py
yaco.recipe.patch.egg-info/PKG-INFO
yaco.recipe.patch.egg-info/SOURCES.txt
yaco.recipe.patch.egg-info/dependency_links.txt
yaco.recipe.patch.egg-info/entry_points.txt
yaco.recipe.patch.egg-info/namespace_packages.txt
yaco.recipe.patch.egg-info/not-zip-safe
yaco.recipe.patch.egg-info/requires.txt
yaco.recipe.patch.egg-info/top_level.txt
yaco/recipe/__init__.py
yaco/recipe/patch/__init__.py
yaco/recipe/patch/tests/__init__.py
yaco/recipe/patch/tests/test_docs.py