Metadata-Version: 1.0
Name: yaco.recipe.patch
Version: 0.3.2.1
Summary: Yet, another buildout recipe for patching
Home-page: http://github.com/ant30/yaco-recipe-patch
Author: Antonio Pérez-Aranda Alcaide
Author-email: ant30tx at gmail.com
License: LGPL
Keywords: buildout patch
Platform: UNKNOWN
Classifier: Framework :: Buildout
Classifier: Intended Audience :: Developers
Classifier: Topic :: Software Development :: Build Tools
Classifier: License :: OSI Approved :: GNU Library or Lesser General Public License (LGPL)
Classifier: Programming Language :: Python
